tac_tasks_validation/__init__.py
tac_tasks_validation/base.py
tac_tasks_validation/exceptions.py
tac_tasks_validation/old_to_new.py
tac_tasks_validation/ont_migration.py
tac_tasks_validation-0.4.dist-info/LICENSE.txt
tac_tasks_validation-0.4.dist-info/METADATA
tac_tasks_validation-0.4.dist-info/WHEEL
tac_tasks_validation-0.4.dist-info/top_level.txt
tac_tasks_validation-0.4.dist-info/RECORD
