Metadata-Version: 2.1
Name: tac-tasks-validation
Version: 0.4
Summary: TAC Tasks input validation
Home-page: https://gitlab.com/horsebridge/tac_tasks_validation.git
Author: Nitin Sidhu
Author-email: nitin.sidhu23@gmail.com
License: MIT
Platform: UNKNOWN
Classifier: License :: OSI Approved :: MIT License
Classifier: Operating System :: OS Independent
Classifier: Programming Language :: Python :: 3.6
Classifier: Programming Language :: Python :: 3.7
Classifier: Programming Language :: Python :: 3.8
Requires-Python: ~=3.7
Requires-Dist: sqlalchemy
Requires-Dist: fibrenest-db-models
Requires-Dist: hns-console-logging
